medblocks/__init__.py
medblocks/client.py
medblocks/cryptography.py
medblocks/errors.py
medblocks/parser.py
medblocks-0.0.2.dist-info/METADATA
medblocks-0.0.2.dist-info/RECORD
medblocks-0.0.2.dist-info/WHEEL
medblocks-0.0.2.dist-info/top_level.txt
