Metadata-Version: 2.1
Name: medblocks
Version: 0.0.2
Summary: MedBlocks python client
Home-page: https://gitlab.com/medblocks/medblocks.py
Author: Sidharth R
Author-email: tornadoalert@gmail.com
License: UNKNOWN
Platform: UNKNOWN
Classifier: Programming Language :: Python :: 3
Classifier: License :: OSI Approved :: MIT License
Classifier: Operating System :: OS Independent
Requires-Python: >=3.2
